{
  "type": "Live2D Physics",
  "physics_hair": [
    {
      "label": "HAIR SIDE L",
      "setup": {
        "length": 0.16,
        "regist": 0.47,
        "mass": 0.17
      },
      "src": [
        {
          "id": "PARAM_ANGLE_X",
          "ptype": "x",
          "scale": 0.007,
          "weight": 0.5
        }
      ],
      "targets": [
        {
          "id": "PARAM_HAIR_SIDE_00",
          "ptype": "angle",
          "scale": 0.022,
          "weight": 0.5
        }
      ]
    },
    {
      "label": "HAIR SIDE R",
      "setup": {
        "length": 0.16,
        "regist": 0.47,
        "mass": 0.18
      },
      "src": [
        {
          "id": "PARAM_ANGLE_X",
          "ptype": "x",
          "scale": 0.008,
          "weight": 0.5
        }
      ],
      "targets": [
        {
          "id": "PARAM_HAIR_SIDE_01",
          "ptype": "angle",
          "scale": 0.022,
          "weight": 0.5
        }
      ]
    },
    {
      "label": "HAIR BACK",
      "setup": {
        "length": 0.2,
        "regist": 0.5,
        "mass": 0.23
      },
      "src": [
        {
          "id": "PARAM_ANGLE_X",
          "ptype": "x",
          "scale": 0.003,
          "weight": 0.7
        }
      ],
      "targets": [
        {
          "id": "PARAM_HAIR_BACK_00",
          "ptype": "angle",
          "scale": 0.022,
          "weight": 0.7
        }
      ]
    },
    {
      "label": "BUST 00",
      "setup": {
        "length": 0.15,
        "regist": 0.5,
        "mass": 0.16
      },
      "src": [
        {
          "id": "PARAM_BODY_ANGLE_X",
          "ptype": "x",
          "scale": 0.009,
          "weight": 0.7
        }
      ],
      "targets": [
        {
          "id": "PARAM_CLOTHES_A",
          "ptype": "angle",
          "scale": 0.022,
          "weight": 0.7
        }
      ]
    },
    {
      "label": "BUST 01",
      "setup": {
        "length": 0.18,
        "regist": 0.5,
        "mass": 0.21
      },
      "src": [
        {
          "id": "PARAM_BODY_ANGLE_X",
          "ptype": "x",
          "scale": 0.011,
          "weight": 0.7
        }
      ],
      "targets": [
        {
          "id": "PARAM_CLOTHES_B",
          "ptype": "angle",
          "scale": 0.022,
          "weight": 0.7
        }
      ]
    },
    {
      "label": "BUST 02",
      "setup": {
        "length": 0.13,
        "regist": 0.5,
        "mass": 0.15
      },
      "src": [
        {
          "id": "PARAM_BODY_ANGLE_X",
          "ptype": "x",
          "scale": 0.015,
          "weight": 0.7
        }
      ],
      "targets": [
        {
          "id": "PARAM_CLOTHES_C",
          "ptype": "angle",
          "scale": 0.022,
          "weight": 0.7
        }
      ]
    },
    {
      "label": "HAIR BACK 01",
      "setup": {
        "length": 0.2,
        "regist": 0.5,
        "mass": 0.23
      },
      "src": [
        {
          "id": "PARAM_HAIR_BACK_00",
          "ptype": "x",
          "scale": 0.05,
          "weight": 0.7
        }
      ],
      "targets": [
        {
          "id": "PARAM_HAIR_BACK_01",
          "ptype": "angle",
          "scale": 0.022,
          "weight": 0.7
        }
      ]
    },
    {
      "label": "BUST 03",
      "setup": {
        "length": 0.17,
        "regist": 0.5,
        "mass": 0.19
      },
      "src": [
        {
          "id": "PARAM_BODY_ANGLE_X",
          "ptype": "x",
          "scale": 0.01,
          "weight": 0.7
        }
      ],
      "targets": [
        {
          "id": "PARAM_CLOTHES_D",
          "ptype": "angle",
          "scale": 0.022,
          "weight": 0.7
        }
      ]
    },
    {
      "label": "BUST 04",
      "setup": {
        "length": 0.16,
        "regist": 0.5,
        "mass": 0.2
      },
      "src": [
        {
          "id": "PARAM_BODY_ANGLE_X",
          "ptype": "x",
          "scale": 0.009,
          "weight": 0.7
        }
      ],
      "targets": [
        {
          "id": "PARAM_CLOTHES_E",
          "ptype": "angle",
          "scale": 0.022,
          "weight": 0.7
        }
      ]
    },
    {
      "label": "BUST 05",
      "setup": {
        "length": 0.14,
        "regist": 0.5,
        "mass": 0.15
      },
      "src": [
        {
          "id": "PARAM_BODY_ANGLE_X",
          "ptype": "x",
          "scale": 0.008,
          "weight": 0.7
        }
      ],
      "targets": [
        {
          "id": "PARAM_CLOTHES_F",
          "ptype": "angle",
          "scale": 0.022,
          "weight": 0.7
        }
      ]
    }
  ]
}
