{
  "skeleton": {
    "hash": "JpHhvM1iGXY",
    "spine": "4.2.93",
    "x": 0,
    "y": 0,
    "width": 504.66,
    "height": 576.07
  },
  "bones": [
    { "name": "root", "color": "9b9b9bff" },
    {
      "name": "bone",
      "parent": "root",
      "length": 61.0,
      "x": 16.54,
      "y": 11.37,
      "rotation": 90.0,
      "scaleX": 1.17,
      "scaleY": 1.17,
      "color": "9b9b9bff"
    },
    {
      "name": "bone2",
      "parent": "bone",
      "length": 30.97,
      "x": 3.77,
      "y": -10.7,
      "rotation": 90.0,
      "scaleX": 2.03,
      "scaleY": 2.03,
      "color": "9b9b9bff"
    },
    {
      "name": "bone3",
      "parent": "root",
      "x": -16.94,
      "y": 1.11,
      "color": "9b9b9bff"
    },
    {
      "name": "bone4",
      "parent": "root",
      "x": -15.7,
      "y": 140.34,
      "scaleX": 1.59,
      "scaleY": 1.59,
      "color": "9b9b9bff"
    }
  ],
  "slots": [
    { "name": "bj0", "bone": "bone", "attachment": "bj0", "blend": "additive" },
    {
      "name": "zx0",
      "bone": "bone2",
      "attachment": "zx0",
      "blend": "additive"
    },
    { "name": "nm0", "bone": "bone4", "attachment": "nm0" },
    {
      "name": "nm1",
      "bone": "bone4",
      "color": "ffb8c360",
      "attachment": "nm0",
      "blend": "additive"
    },
    { "name": "dg0", "bone": "bone3", "attachment": "dg0", "blend": "additive" }
  ],
  "skins": [
    {
      "name": "default",
      "attachments": {
        "bj0": {
          "bj0": {
            "y": 8.3e-7,
            "rotation": -90.0,
            "width": 431,
            "height": 392,
            "color": "ffffffff"
          },
          "bj1": {
            "y": 8.3e-7,
            "rotation": -90.0,
            "width": 431,
            "height": 392,
            "color": "ffffffff"
          },
          "bj10": {
            "y": 8.3e-7,
            "rotation": -90.0,
            "width": 431,
            "height": 392,
            "color": "ffffffff"
          },
          "bj2": {
            "y": 8.3e-7,
            "rotation": -90.0,
            "width": 431,
            "height": 392,
            "color": "ffffffff"
          },
          "bj3": {
            "y": 8.3e-7,
            "rotation": -90.0,
            "width": 431,
            "height": 392,
            "color": "ffffffff"
          },
          "bj4": {
            "y": 8.3e-7,
            "rotation": -90.0,
            "width": 431,
            "height": 392,
            "color": "ffffffff"
          },
          "bj5": {
            "y": 8.3e-7,
            "rotation": -90.0,
            "width": 431,
            "height": 392,
            "color": "ffffffff"
          },
          "bj6": {
            "y": 8.3e-7,
            "rotation": -90.0,
            "width": 431,
            "height": 392,
            "color": "ffffffff"
          },
          "bj7": {
            "y": 8.3e-7,
            "rotation": -90.0,
            "width": 431,
            "height": 392,
            "color": "ffffffff"
          },
          "bj8": {
            "y": 8.3e-7,
            "rotation": -90.0,
            "width": 431,
            "height": 392,
            "color": "ffffffff"
          },
          "bj9": {
            "x": -19.86,
            "y": -2.1e-6,
            "rotation": -90.0,
            "width": 431,
            "height": 392,
            "color": "ffffffff"
          }
        },
        "dg0": {
          "dg0": { "width": 244, "height": 230, "color": "ffffffff" },
          "dg1": { "width": 244, "height": 230, "color": "ffffffff" },
          "dg2": { "width": 244, "height": 230, "color": "ffffffff" },
          "dg3": { "width": 244, "height": 230, "color": "ffffffff" },
          "dg4": { "width": 244, "height": 230, "color": "ffffffff" },
          "dg5": { "width": 244, "height": 230, "color": "ffffffff" }
        },
        "nm0": {
          "nm0": {
            "scaleX": 1.22,
            "width": 208,
            "height": 273,
            "color": "ffffffff"
          },
          "nm1": { "width": 208, "height": 273, "color": "ffffffff" },
          "nm10": { "width": 208, "height": 273, "color": "ffffffff" },
          "nm2": { "width": 208, "height": 273, "color": "ffffffff" },
          "nm3": { "width": 208, "height": 273, "color": "ffffffff" },
          "nm4": { "width": 208, "height": 273, "color": "ffffffff" },
          "nm5": { "width": 208, "height": 273, "color": "ffffffff" },
          "nm6": { "width": 208, "height": 273, "color": "ffffffff" },
          "nm7": { "width": 208, "height": 273, "color": "ffffffff" },
          "nm8": { "width": 208, "height": 273, "color": "ffffffff" },
          "nm9": { "width": 208, "height": 273, "color": "ffffffff" }
        },
        "nm1": {
          "nm0": {
            "scaleX": 1.22,
            "width": 208,
            "height": 273,
            "color": "ffffffff"
          },
          "nm1": { "width": 208, "height": 273, "color": "ffffffff" },
          "nm10": { "width": 208, "height": 273, "color": "ffffffff" },
          "nm2": { "width": 208, "height": 273, "color": "ffffffff" },
          "nm3": { "width": 208, "height": 273, "color": "ffffffff" },
          "nm4": { "width": 208, "height": 273, "color": "ffffffff" },
          "nm5": { "width": 208, "height": 273, "color": "ffffffff" },
          "nm6": { "width": 208, "height": 273, "color": "ffffffff" },
          "nm7": { "width": 208, "height": 273, "color": "ffffffff" },
          "nm8": { "width": 208, "height": 273, "color": "ffffffff" },
          "nm9": { "width": 208, "height": 273, "color": "ffffffff" }
        },
        "zx0": {
          "zx0": {
            "x": 11.33,
            "y": 1.9e-6,
            "rotation": -180.0,
            "width": 128,
            "height": 131,
            "color": "ffffffff"
          },
          "zx1": {
            "x": -4.2,
            "rotation": -180.0,
            "width": 199,
            "height": 170,
            "color": "ffffffff"
          },
          "zx2": {
            "x": -4.2,
            "rotation": -180.0,
            "width": 198,
            "height": 160,
            "color": "ffffffff"
          },
          "zx3": {
            "x": 9.5e-7,
            "y": 4.8e-7,
            "rotation": -180.0,
            "width": 193,
            "height": 160,
            "color": "ffffffff"
          },
          "zx4": {
            "x": 1.26,
            "y": 9.5e-7,
            "rotation": -180.0,
            "width": 187,
            "height": 154,
            "color": "ffffffff"
          }
        }
      }
    }
  ],
  "animations": {
    "idle": {
      "slots": {
        "bj0": {
          "attachment": [
            { "name": "bj0" },
            { "time": 0.04159, "name": "bj1" },
            { "time": 0.12478, "name": "bj2" },
            { "time": 0.16667, "name": "bj3" },
            { "time": 0.20797, "name": "bj4" },
            { "time": 0.29116, "name": "bj5" },
            { "time": 0.33276, "name": "bj6" },
            { "time": 0.41595, "name": "bj7" },
            { "time": 0.45754, "name": "bj8" },
            { "time": 0.49914, "name": "bj9" },
            { "time": 0.58233, "name": "bj10" },
            { "time": 0.62392 }
          ]
        },
        "dg0": {
          "attachment": [
            {},
            { "time": 0.3 },
            { "time": 0.33333, "name": "dg0" },
            { "time": 0.36667, "name": "dg1" },
            { "time": 0.4, "name": "dg2" },
            { "time": 0.43333, "name": "dg3" },
            { "time": 0.46667, "name": "dg4" },
            { "time": 0.5, "name": "dg5" },
            { "time": 0.53333 },
            { "time": 0.66667 }
          ]
        },
        "nm0": {
          "attachment": [
            {},
            { "time": 0.06915 },
            { "time": 0.11244, "name": "nm0" },
            { "time": 0.15572, "name": "nm1" },
            { "time": 0.199, "name": "nm2" },
            { "time": 0.24228, "name": "nm3" },
            { "time": 0.28557, "name": "nm4" },
            { "time": 0.32885, "name": "nm5" },
            { "time": 0.37213, "name": "nm6" },
            { "time": 0.41542, "name": "nm7" },
            { "time": 0.4587, "name": "nm8" },
            { "time": 0.50198, "name": "nm9" },
            { "time": 0.54526, "name": "nm10" },
            { "time": 0.58855 },
            { "time": 0.66667 }
          ]
        },
        "nm1": {
          "attachment": [
            {},
            { "time": 0.06915 },
            { "time": 0.11244, "name": "nm0" },
            { "time": 0.15572, "name": "nm1" },
            { "time": 0.199, "name": "nm2" },
            { "time": 0.24228, "name": "nm3" },
            { "time": 0.28557, "name": "nm4" },
            { "time": 0.32885, "name": "nm5" },
            { "time": 0.37213, "name": "nm6" },
            { "time": 0.41542, "name": "nm7" },
            { "time": 0.4587, "name": "nm8" },
            { "time": 0.50198, "name": "nm9" },
            { "time": 0.53333, "name": "nm9" },
            { "time": 0.54526, "name": "nm10" },
            { "time": 0.58855 },
            { "time": 0.66667 }
          ]
        },
        "zx0": {
          "attachment": [
            { "name": "zx0" },
            { "time": 0.06598, "name": "zx1" },
            { "time": 0.13196, "name": "zx2" },
            { "time": 0.19794, "name": "zx3" },
            { "time": 0.26392, "name": "zx4" },
            { "time": 0.3299 }
          ]
        }
      },
      "bones": {
        "bone": {
          "rotate": [{ "curve": "stepped" }, { "time": 0.62392 }],
          "translate": [{ "curve": "stepped" }, { "time": 0.62392 }],
          "scale": [{}, { "time": 0.62392, "x": 1.88, "y": 1.88 }],
          "shear": [{ "curve": "stepped" }, { "time": 0.62392 }]
        },
        "bone2": {
          "rotate": [
            { "curve": "stepped" },
            { "time": 0.62392, "curve": "stepped" },
            { "time": 0.66667 }
          ],
          "translate": [
            { "curve": "stepped" },
            { "time": 0.62392, "curve": "stepped" },
            { "time": 0.66667 }
          ],
          "scale": [
            { "curve": "stepped" },
            { "time": 0.62392, "curve": "stepped" },
            { "time": 0.66667 }
          ],
          "shear": [
            { "curve": "stepped" },
            { "time": 0.62392, "curve": "stepped" },
            { "time": 0.66667 }
          ]
        },
        "bone3": {
          "scale": [
            { "curve": "stepped" },
            { "time": 0.3 },
            { "time": 0.53333, "x": 1.9, "y": 1.9, "curve": "stepped" },
            { "time": 0.66667, "x": 1.9, "y": 1.9 }
          ]
        },
        "bone4": {
          "scale": [
            {},
            { "time": 0.1, "x": 1.32, "y": 1.19, "curve": "stepped" },
            { "time": 0.66667, "x": 1.32, "y": 1.19 }
          ]
        },
        "root": {
          "rotate": [{ "curve": "stepped" }, { "time": 0.62392 }],
          "translate": [{ "curve": "stepped" }, { "time": 0.62392 }],
          "scale": [
            { "x": 1.31, "y": 1.31, "curve": "stepped" },
            { "time": 0.62392, "x": 1.31, "y": 1.31 }
          ],
          "shear": [{ "curve": "stepped" }, { "time": 0.62392 }]
        }
      }
    },
    "pseudo_setup_pose": { "drawOrder": [{}] }
  }
}
