{
  "skeleton": {
    "hash": "NdGMDiEoWFI",
    "spine": "4.2.93",
    "x": 0,
    "y": 0,
    "width": 902.15,
    "height": 625.97
  },
  "bones": [
    { "name": "root", "color": "9b9b9bff" },
    {
      "name": "a6",
      "parent": "root",
      "length": 42.3,
      "x": -8.5,
      "y": 3.0,
      "scaleX": -1,
      "color": "9b9b9bff"
    },
    {
      "name": "bone",
      "parent": "root",
      "length": 68.47,
      "x": -1.07,
      "y": 14.64,
      "rotation": 90,
      "scaleX": 2.32,
      "scaleY": 2.32,
      "color": "9b9b9bff"
    },
    {
      "name": "bone2",
      "parent": "root",
      "length": 79.4,
      "x": -43.01,
      "y": 161.34,
      "rotation": -2.16,
      "scaleX": 1.83,
      "scaleY": 1.83,
      "color": "9b9b9bff"
    },
    {
      "name": "bone3",
      "parent": "root",
      "length": 50.92,
      "x": -23.04,
      "y": 35.85,
      "rotation": 1.68,
      "scaleX": 1.92,
      "scaleY": 1.92,
      "color": "9b9b9bff"
    },
    {
      "name": "bone4",
      "parent": "root",
      "length": 70.32,
      "x": -136.05,
      "y": 108.02,
      "scaleX": 1.32,
      "scaleY": 1.32,
      "color": "9b9b9bff"
    },
    {
      "name": "bone5",
      "parent": "root",
      "length": 38.83,
      "x": -244.25,
      "y": 27.31,
      "scaleX": -2.73,
      "scaleY": 2.73,
      "color": "9b9b9bff"
    },
    {
      "name": "bone6",
      "parent": "root",
      "length": 38.83,
      "x": 169.83,
      "y": 27.31,
      "scaleX": 2.73,
      "scaleY": 2.73,
      "color": "9b9b9bff"
    }
  ],
  "slots": [
    { "name": "a14", "bone": "bone5", "blend": "additive" },
    { "name": "a15", "bone": "bone6", "blend": "additive" },
    { "name": "a6", "bone": "a6", "color": "00bfffff", "blend": "additive" },
    {
      "name": "tf0",
      "bone": "bone",
      "color": "2900ffff",
      "attachment": "tf0",
      "blend": "additive"
    },
    {
      "name": "dga1",
      "bone": "bone2",
      "attachment": "dga1",
      "blend": "additive"
    },
    {
      "name": "zjd1",
      "bone": "bone3",
      "attachment": "zjd1",
      "blend": "additive"
    },
    { "name": "a0", "bone": "bone4", "attachment": "a0", "blend": "additive" }
  ],
  "skins": [
    {
      "name": "default",
      "attachments": {
        "a0": {
          "a0": { "width": 681, "height": 407, "color": "ffffffff" },
          "a1": {
            "x": 67.94,
            "width": 395,
            "height": 332,
            "color": "ffffffff"
          },
          "a2": {
            "x": 113.23,
            "width": 278,
            "height": 289,
            "color": "ffffffff"
          },
          "a3": {
            "x": 135.88,
            "width": 132,
            "height": 170,
            "color": "ffffffff"
          }
        },
        "a14": {
          "a13": { "width": 216, "height": 130, "color": "ffffffff" },
          "a14": {
            "x": 10.99,
            "y": -1.1,
            "width": 213,
            "height": 128,
            "color": "ffffffff"
          },
          "a15": {
            "x": 14.65,
            "width": 213,
            "height": 128,
            "color": "ffffffff"
          },
          "a16": {
            "x": 18.31,
            "width": 213,
            "height": 128,
            "color": "ffffffff"
          },
          "a17": {
            "x": 21.98,
            "width": 212,
            "height": 126,
            "color": "ffffffff"
          },
          "a18": {
            "x": 25.64,
            "width": 208,
            "height": 122,
            "color": "ffffffff"
          },
          "a19": {
            "x": -10.99,
            "y": 3.66,
            "width": 113,
            "height": 103,
            "color": "ffffffff"
          }
        },
        "a15": {
          "a13": { "width": 216, "height": 130, "color": "ffffffff" },
          "a14": {
            "x": 10.99,
            "y": -1.1,
            "width": 213,
            "height": 128,
            "color": "ffffffff"
          },
          "a15": {
            "x": 14.65,
            "width": 213,
            "height": 128,
            "color": "ffffffff"
          },
          "a16": {
            "x": 18.31,
            "width": 213,
            "height": 128,
            "color": "ffffffff"
          },
          "a17": {
            "x": 21.98,
            "width": 212,
            "height": 126,
            "color": "ffffffff"
          },
          "a18": {
            "x": 25.64,
            "width": 208,
            "height": 122,
            "color": "ffffffff"
          },
          "a19": {
            "x": -10.99,
            "y": 3.66,
            "width": 113,
            "height": 103,
            "color": "ffffffff"
          }
        },
        "a6": {
          "a6": {
            "x": 16.0,
            "y": 48.0,
            "width": 533,
            "height": 450,
            "color": "ffffffff"
          },
          "a7": {
            "x": 16.0,
            "y": 48.0,
            "width": 533,
            "height": 450,
            "color": "ffffffff"
          },
          "a8": {
            "x": 16.0,
            "y": 48.0,
            "width": 533,
            "height": 450,
            "color": "ffffffff"
          },
          "a9": {
            "x": 16.0,
            "y": 48.0,
            "width": 533,
            "height": 450,
            "color": "ffffffff"
          }
        },
        "dga1": {
          "dga1": {
            "x": -10.74,
            "y": -5.89,
            "rotation": 2.16,
            "width": 239,
            "height": 251,
            "color": "ffffffff"
          },
          "dga2": {
            "x": 16.42,
            "y": 0.61971,
            "rotation": 2.16,
            "width": 163,
            "height": 246,
            "color": "ffffffff"
          },
          "dga3": {
            "x": 15.86,
            "y": 15.4,
            "rotation": 2.16,
            "width": 112,
            "height": 238,
            "color": "ffffffff"
          },
          "dga4": {
            "x": 15.8,
            "y": 17.04,
            "rotation": 2.16,
            "width": 112,
            "height": 241,
            "color": "ffffffff"
          },
          "dga5": {
            "x": 15.8,
            "y": 17.04,
            "rotation": 2.16,
            "width": 111,
            "height": 243,
            "color": "ffffffff"
          }
        },
        "tf0": {
          "tf0": {
            "rotation": -90,
            "width": 224,
            "height": 224,
            "color": "ffffffff"
          }
        },
        "zjd1": {
          "zjd1": {
            "rotation": -1.68,
            "width": 221,
            "height": 151,
            "color": "ffffffff"
          },
          "zjd2": {
            "x": 11.04,
            "y": 20.54,
            "rotation": -1.68,
            "width": 316,
            "height": 212,
            "color": "ffffffff"
          },
          "zjd3": {
            "x": 10.28,
            "y": 30.47,
            "rotation": -1.68,
            "width": 321,
            "height": 233,
            "color": "ffffffff"
          },
          "zjd4": {
            "x": 9.26,
            "y": 31.02,
            "rotation": -1.68,
            "width": 325,
            "height": 233,
            "color": "ffffffff"
          },
          "zjd5": {
            "x": 9.27,
            "y": 31.54,
            "rotation": -1.68,
            "width": 327,
            "height": 232,
            "color": "ffffffff"
          },
          "zjd6": {
            "x": 9.29,
            "y": 32.06,
            "rotation": -1.68,
            "width": 323,
            "height": 231,
            "color": "ffffffff"
          },
          "zjd7": {
            "x": 9.3,
            "y": 32.59,
            "rotation": -1.68,
            "width": 323,
            "height": 230,
            "color": "ffffffff"
          },
          "zjd8": {
            "x": 7.05,
            "y": 26.91,
            "rotation": -1.68,
            "width": 319,
            "height": 212,
            "color": "ffffffff"
          },
          "zjd9": {
            "x": 0.91964,
            "y": 31.27,
            "rotation": -1.68,
            "width": 317,
            "height": 210,
            "color": "ffffffff"
          }
        }
      }
    }
  ],
  "animations": {
    "idle": {
      "slots": {
        "a0": {
          "attachment": [
            { "name": "a0" },
            { "time": 0.06667, "name": "a1" },
            { "time": 0.13333, "name": "a2" },
            { "time": 0.2, "name": "a3" },
            { "time": 0.26667 }
          ]
        },
        "a14": {
          "attachment": [
            {},
            { "time": 0.30733, "name": "a13" },
            { "time": 0.35855, "name": "a14" },
            { "time": 0.40977, "name": "a15" },
            { "time": 0.46099, "name": "a16" },
            { "time": 0.51222, "name": "a17" },
            { "time": 0.56344, "name": "a18" },
            { "time": 0.61466, "name": "a19" },
            { "time": 0.66588 }
          ]
        },
        "a15": {
          "attachment": [
            {},
            { "time": 0.30733, "name": "a13" },
            { "time": 0.35855, "name": "a14" },
            { "time": 0.40977, "name": "a15" },
            { "time": 0.46099, "name": "a16" },
            { "time": 0.51222, "name": "a17" },
            { "time": 0.56344, "name": "a18" },
            { "time": 0.61466, "name": "a19" },
            { "time": 0.66588 }
          ]
        },
        "a6": {
          "attachment": [
            { "name": "a6" },
            { "time": 0.05122, "name": "a6" },
            { "time": 0.10244, "name": "a6" },
            { "time": 0.15366, "name": "a7" },
            { "time": 0.20489, "name": "a8" },
            { "time": 0.25611, "name": "a9" },
            { "time": 0.30733 },
            { "time": 0.66588 }
          ]
        },
        "dga1": {
          "attachment": [
            { "name": "dga1" },
            { "time": 0.05122, "name": "dga2" },
            { "time": 0.10244, "name": "dga3" },
            { "time": 0.15366, "name": "dga4" },
            { "time": 0.20489, "name": "dga5" },
            { "time": 0.25611 },
            { "time": 0.66588 }
          ]
        },
        "tf0": {
          "attachment": [{ "name": "tf0" }, { "time": 0.66588, "name": "tf0" }],
          "rgba": [
            {
              "color": "0072ffff",
              "curve": [
                0.04061, 0, 0.09442, 0.08434, 0.04061, 0.44706, 0.09442,
                0.27225, 0.04061, 1, 0.09442, 1, 0.04061, 1, 0.09442, 1
              ]
            },
            {
              "time": 0.15366,
              "color": "3700ffff",
              "curve": [
                0.17031, 0.2039, 0.18747, 0.1907, 0.17031, 0.03891, 0.18747,
                0.08245, 0.17031, 1, 0.18747, 1, 0.17031, 1, 0.18747, 1
              ]
            },
            {
              "time": 0.20489,
              "color": "2d21ffff",
              "curve": [
                0.27413, 0.21167, 0.34758, 0.25711, 0.27413, 0.10897, 0.34758,
                0.08259, 0.27413, 1, 0.34758, 1, 0.27413, 0.97275, 0.34758,
                0.93757
              ]
            },
            {
              "time": 0.40977,
              "color": "4c0fffe7",
              "curve": [
                0.47242, 0.49182, 0.52656, 0.66961, 0.47242, 0.14956, 0.52656,
                0.23281, 0.47242, 1, 0.52656, 1, 0.47242, 0.55062, 0.52656,
                0.22468
              ]
            },
            { "time": 0.56344, "color": "ca4aff00" }
          ]
        },
        "zjd1": {
          "attachment": [
            {},
            { "time": 0.15366, "name": "zjd1" },
            { "time": 0.20489, "name": "zjd2" },
            { "time": 0.25611, "name": "zjd3" },
            { "time": 0.30733, "name": "zjd4" },
            { "time": 0.35855, "name": "zjd5" },
            { "time": 0.40977, "name": "zjd6" },
            { "time": 0.46099, "name": "zjd7" },
            { "time": 0.51222, "name": "zjd8" },
            { "time": 0.56344, "name": "zjd9" },
            { "time": 0.61466 },
            { "time": 0.66588 }
          ]
        }
      },
      "bones": {
        "a6": {
          "rotate": [{ "curve": "stepped" }, { "time": 0.66588 }],
          "translate": [{ "x": 17.13, "y": -11.42 }],
          "scale": [
            { "x": 0.72168, "y": 0.44909 },
            { "time": 0.05122, "x": 0.80959, "y": 0.7018 },
            { "time": 0.10244, "curve": "stepped" },
            { "time": 0.66588 }
          ],
          "shear": [{ "curve": "stepped" }, { "time": 0.66588 }]
        },
        "bone": {
          "rotate": [
            { "value": 9.94, "curve": "stepped" },
            { "time": 0.66588, "value": 9.94 }
          ],
          "translate": [
            { "x": 8.67, "y": 153.68 },
            { "time": 0.10244, "x": 3.5e-6, "y": 78.53 },
            { "time": 0.15366, "x": -14.64, "y": 29.28 }
          ],
          "scale": [
            { "x": 1.68, "y": 1.6 },
            { "time": 0.05122, "x": 2.04, "y": 1.05 },
            { "time": 0.10244, "x": 1.23, "y": 0.79928 },
            { "time": 0.15366, "x": 1.43, "y": 1.37 },
            { "time": 0.56344, "x": 1.1, "y": 0.79928, "curve": "stepped" },
            { "time": 0.66588, "x": 1.1, "y": 0.79928 }
          ],
          "shear": [{ "curve": "stepped" }, { "time": 0.66588 }]
        },
        "bone2": {
          "rotate": [{ "curve": "stepped" }, { "time": 0.66588 }],
          "translate": [
            { "x": -51.98, "y": 93.81 },
            { "time": 0.05122, "x": -15.95, "y": 64.26 }
          ],
          "scale": [
            { "x": 1.4, "y": 1.5 },
            { "time": 0.05122, "x": 1.24, "y": 1.24, "curve": "stepped" },
            { "time": 0.66588, "x": 1.24, "y": 1.24 }
          ],
          "shear": [{ "curve": "stepped" }, { "time": 0.66588 }]
        },
        "bone3": {
          "rotate": [{ "curve": "stepped" }, { "time": 0.66588 }],
          "translate": [{}],
          "scale": [
            { "x": 0.86149, "y": 0.86149 },
            { "time": 0.61466, "x": 1.09, "y": 1.09, "curve": "stepped" },
            { "time": 0.66588, "x": 1.09, "y": 1.09 }
          ],
          "shear": [{ "curve": "stepped" }, { "time": 0.66588 }]
        },
        "bone4": {
          "rotate": [{}],
          "translate": [{ "x": -53.51, "y": 90.96 }],
          "scale": [{ "x": 0.85853, "y": 1.29 }],
          "shear": [{}]
        },
        "bone5": {
          "rotate": [{ "curve": "stepped" }, { "time": 0.66588 }],
          "translate": [{ "x": 32.64 }, { "time": 0.66588, "x": -44.67 }],
          "scale": [
            { "x": 1.05, "y": 0.94609, "curve": "stepped" },
            { "time": 0.66588, "x": 1.05, "y": 0.94609 }
          ],
          "shear": [{ "curve": "stepped" }, { "time": 0.66588 }]
        },
        "bone6": {
          "rotate": [{ "curve": "stepped" }, { "time": 0.66588 }],
          "translate": [{}],
          "scale": [{ "curve": "stepped" }, { "time": 0.66588 }],
          "shear": [{ "curve": "stepped" }, { "time": 0.66588 }]
        },
        "root": {
          "rotate": [{ "curve": "stepped" }, { "time": 0.66588 }],
          "translate": [{}],
          "scale": [{ "curve": "stepped" }, { "time": 0.66588 }],
          "shear": [{ "curve": "stepped" }, { "time": 0.66588 }]
        }
      },
      "drawOrder": [{}, { "time": 0.66588 }]
    },
    "pseudo_setup_pose": { "drawOrder": [{}] }
  }
}
