{
  "skeleton": {
    "hash": "pqPvbDPEkHw",
    "spine": "4.2.93",
    "x": 0,
    "y": 0,
    "width": 394.88,
    "height": 374.28
  },
  "bones": [
    { "name": "root", "scaleX": 1.13, "scaleY": 1.13, "color": "9b9b9bff" },
    {
      "name": "bone2",
      "parent": "root",
      "x": -11.22,
      "y": -5.23,
      "color": "9b9b9bff"
    },
    {
      "name": "bone3",
      "parent": "root",
      "x": -14.5,
      "y": 15.0,
      "color": "9b9b9bff"
    }
  ],
  "slots": [
    {
      "name": "resource/attack_guang_8",
      "bone": "bone3",
      "attachment": "resource/attack_guang_008",
      "blend": "additive"
    },
    {
      "name": "resource/attack_guang_008",
      "bone": "bone2",
      "attachment": "resource/attack_shouji_016",
      "blend": "additive"
    }
  ],
  "skins": [
    {
      "name": "default",
      "attachments": {
        "resource/attack_guang_008": {
          "resource/attack_shouji_008": {
            "width": 337,
            "height": 321,
            "color": "ffffffff"
          },
          "resource/attack_shouji_009": {
            "width": 337,
            "height": 321,
            "color": "ffffffff"
          },
          "resource/attack_shouji_010": {
            "width": 337,
            "height": 321,
            "color": "ffffffff"
          },
          "resource/attack_shouji_011": {
            "width": 337,
            "height": 321,
            "color": "ffffffff"
          },
          "resource/attack_shouji_012": {
            "width": 337,
            "height": 321,
            "color": "ffffffff"
          },
          "resource/attack_shouji_013": {
            "width": 337,
            "height": 321,
            "color": "ffffffff"
          },
          "resource/attack_shouji_014": {
            "width": 337,
            "height": 321,
            "color": "ffffffff"
          },
          "resource/attack_shouji_015": {
            "width": 337,
            "height": 321,
            "color": "ffffffff"
          },
          "resource/attack_shouji_016": {
            "width": 337,
            "height": 321,
            "color": "ffffffff"
          },
          "resource/attack_shouji_017": {
            "width": 337,
            "height": 321,
            "color": "ffffffff"
          },
          "resource/attack_shouji_018": {
            "width": 337,
            "height": 321,
            "color": "ffffffff"
          },
          "resource/attack_shouji_019": {
            "width": 337,
            "height": 321,
            "color": "ffffffff"
          },
          "resource/attack_shouji_020": {
            "width": 337,
            "height": 321,
            "color": "ffffffff"
          },
          "resource/attack_shouji_021": {
            "width": 337,
            "height": 321,
            "color": "ffffffff"
          }
        },
        "resource/attack_guang_8": {
          "resource/attack_guang_008": {
            "x": 16.02,
            "y": -9.75,
            "width": 337,
            "height": 321,
            "color": "ffffffff"
          }
        }
      }
    }
  ],
  "animations": {
    "idle": {
      "slots": {
        "resource/attack_guang_008": {
          "attachment": [
            { "name": "resource/attack_shouji_008" },
            { "time": 0.03534, "name": "resource/attack_shouji_009" },
            { "time": 0.07068, "name": "resource/attack_shouji_010" },
            { "time": 0.10603, "name": "resource/attack_shouji_011" },
            { "time": 0.14137, "name": "resource/attack_shouji_012" },
            { "time": 0.17671, "name": "resource/attack_shouji_013" },
            { "time": 0.21213, "name": "resource/attack_shouji_014" },
            { "time": 0.25113, "name": "resource/attack_shouji_015" },
            { "time": 0.29014, "name": "resource/attack_shouji_016" },
            { "time": 0.32914, "name": "resource/attack_shouji_017" },
            { "time": 0.36815, "name": "resource/attack_shouji_018" },
            { "time": 0.40854, "name": "resource/attack_shouji_019" },
            { "time": 0.45448, "name": "resource/attack_shouji_020" },
            { "time": 0.50042, "name": "resource/attack_shouji_021" },
            { "time": 0.55697 },
            { "time": 0.6 },
            { "time": 0.66667 }
          ]
        },
        "resource/attack_guang_8": {
          "attachment": [
            { "name": "resource/attack_guang_008" },
            { "time": 0.6, "name": "resource/attack_guang_008" },
            { "time": 0.66667, "name": "resource/attack_guang_008" }
          ],
          "rgba": [
            { "color": "0036ffff" },
            { "time": 0.6, "color": "0036ff00" }
          ]
        }
      },
      "bones": {
        "bone2": {
          "rotate": [
            { "curve": "stepped" },
            { "time": 0.6, "curve": "stepped" },
            { "time": 0.66667 }
          ],
          "translate": [
            { "curve": "stepped" },
            { "time": 0.6, "curve": "stepped" },
            { "time": 0.66667 }
          ],
          "scale": [
            { "curve": "stepped" },
            { "time": 0.6, "curve": "stepped" },
            { "time": 0.66667 }
          ],
          "shear": [
            { "curve": "stepped" },
            { "time": 0.6, "curve": "stepped" },
            { "time": 0.66667 }
          ]
        },
        "bone3": {
          "rotate": [
            { "curve": "stepped" },
            { "time": 0.6, "curve": "stepped" },
            { "time": 0.66667 }
          ],
          "translate": [
            { "curve": "stepped" },
            { "time": 0.6, "curve": "stepped" },
            { "time": 0.66667 }
          ],
          "scale": [
            {},
            { "time": 0.6, "x": 1.31, "y": 1.31, "curve": "stepped" },
            { "time": 0.66667, "x": 1.31, "y": 1.31 }
          ],
          "shear": [
            { "curve": "stepped" },
            { "time": 0.6, "curve": "stepped" },
            { "time": 0.66667 }
          ]
        },
        "root": {
          "rotate": [
            { "curve": "stepped" },
            { "time": 0.6, "curve": "stepped" },
            { "time": 0.66667 }
          ],
          "translate": [
            { "curve": "stepped" },
            { "time": 0.6, "curve": "stepped" },
            { "time": 0.66667 }
          ],
          "scale": [
            { "x": 1.89, "y": 1.89, "curve": "stepped" },
            { "time": 0.6, "x": 1.89, "y": 1.89, "curve": "stepped" },
            { "time": 0.66667, "x": 1.89, "y": 1.89 }
          ],
          "shear": [
            { "curve": "stepped" },
            { "time": 0.6, "curve": "stepped" },
            { "time": 0.66667 }
          ]
        }
      },
      "drawOrder": [{}, { "time": 0.6 }, { "time": 0.66667 }]
    },
    "pseudo_setup_pose": { "drawOrder": [{}] }
  }
}
